cocorahs.py
cocorahs-0.1.3.dist-info/entry_points.txt
cocorahs-0.1.3.dist-info/LICENSE
cocorahs-0.1.3.dist-info/WHEEL
cocorahs-0.1.3.dist-info/METADATA
cocorahs-0.1.3.dist-info/RECORD
