Metadata-Version: 2.1
Name: cocorahs
Version: 0.1.3
Summary: An API and CLI for reporting CoCoRaHS observations.
Home-page: https://github.com/dschep/PyCoCoraHS
License: UNKNOWN
Author: Daniel Schep
Author-email: dschep@gmail.com
Requires-Python: >= 3.6
Classifier: License :: OSI Approved :: GNU General Public License v3 or later (GPLv3+)
Requires-Dist: requests >= 2.24.0
Requires-Dist: click >= 7.1.2
